[{"msg":"开始语音输入","ts":1662547662689},{"msg":"识别结束","uttr":"新建圆形在这里使得它的文本为明暗","ts":1662547668667},{"msg":"结束语音输入","ts":1662547668683},{"msg":"识别结束","uttr":"新建圆形在这里使得它的文本为明暗","ts":1662547668694},{"msg":"系统接收指令输入","uttr":"新建圆形在这里使得它的文本为明暗","traceNum":1,"ts":1662547672718},{"msg":"解析结束","create":true,"copy":false,"arrow":false,"traceEleNum":0,"tracePosNum":1,"involvedEleNum":2,"itEleNum":0,"attrChange":1,"posRelated":true,"ts":1662547672731},{"msg":"指令执行结束","cdtNum":0,"ts":1662547672746},{"msg":"系统接收指令输入","uttr":"新建圆形在这里使得它的文本为明暗","traceNum":1,"ts":1662547674792},{"msg":"解析结束","create":true,"copy":false,"arrow":false,"traceEleNum":0,"tracePosNum":1,"involvedEleNum":2,"itEleNum":0,"attrChange":1,"posRelated":true,"ts":1662547674803},{"msg":"指令执行结束","cdtNum":0,"ts":1662547674814},{"msg":"系统接收指令输入","uttr":"新建圆形在这里使得它的文本为明暗","traceNum":1,"ts":1662547680021},{"msg":"解析结束","create":true,"copy":false,"arrow":false,"traceEleNum":0,"tracePosNum":1,"involvedEleNum":2,"itEleNum":0,"attrChange":1,"posRelated":true,"ts":1662547680034},{"msg":"指令执行结束","cdtNum":0,"ts":1662547680046},{"msg":"系统接收指令输入","uttr":"新建圆形在这里使得它的文本为明暗","traceNum":1,"ts":1662547681397},{"msg":"解析结束","create":true,"copy":false,"arrow":false,"traceEleNum":0,"tracePosNum":1,"involvedEleNum":2,"itEleNum":0,"attrChange":1,"posRelated":true,"ts":1662547681409},{"msg":"指令执行结束","cdtNum":0,"ts":1662547681421},{"msg":"输入框文本变化","text":"新建圆形在这里使得它的文本为明","ts":1662547685791},{"msg":"系统接收指令输入","uttr":"新建圆形在这里使得它的文本为明","traceNum":1,"ts":1662547691824},{"msg":"解析结束","create":true,"copy":false,"arrow":false,"traceEleNum":0,"tracePosNum":1,"involvedEleNum":2,"itEleNum":0,"attrChange":1,"posRelated":true,"ts":1662547691837},{"msg":"指令执行结束","cdtNum":0,"ts":1662547691848},{"msg":"切换功能栏TAG_DISP_SET_GLOBAL","ts":1662547697343},{"msg":"清空路径","ts":1662547698248},{"msg":"系统接收指令输入","uttr":"新建圆形在这里使得它的文本为明","traceNum":1,"ts":1662547699843},{"msg":"解析结束","create":true,"copy":false,"arrow":false,"traceEleNum":0,"tracePosNum":1,"involvedEleNum":2,"itEleNum":0,"attrChange":1,"posRelated":true,"ts":1662547699859},{"msg":"指令执行结束","cdtNum":0,"ts":1662547699871},{"msg":"输入框文本变化","text":"新建圆形在这里使得它的文本为","ts":1662547704111},{"msg":"输入框文本变化","text":"新建圆形在这里使得它的文本为暗","ts":1662547705506},{"msg":"系统接收指令输入","uttr":"新建圆形在这里使得它的文本为暗","traceNum":1,"ts":1662547710410},{"msg":"解析结束","create":true,"copy":false,"arrow":false,"traceEleNum":0,"tracePosNum":1,"involvedEleNum":2,"itEleNum":0,"attrChange":1,"posRelated":true,"ts":1662547710429},{"msg":"指令执行结束","cdtNum":0,"ts":1662547710441},{"msg":"系统接收指令输入","uttr":"新建圆形在这里使得它的文本为暗","traceNum":1,"ts":1662547712128},{"msg":"解析结束","create":true,"copy":false,"arrow":false,"traceEleNum":0,"tracePosNum":1,"involvedEleNum":2,"itEleNum":0,"attrChange":1,"posRelated":true,"ts":1662547712144},{"msg":"指令执行结束","cdtNum":0,"ts":1662547712154},{"msg":"输入框文本变化","text":"新建圆形在这里使得它的文本为","ts":1662547714878},{"msg":"输入框文本变化","text":"新建圆形在这里使得它的文本为明明","ts":1662547716641},{"msg":"系统接收指令输入","uttr":"新建圆形在这里使得它的文本为明明","traceNum":1,"ts":1662547720584},{"msg":"解析结束","create":true,"copy":false,"arrow":false,"traceEleNum":0,"tracePosNum":1,"involvedEleNum":2,"itEleNum":0,"attrChange":1,"posRelated":true,"ts":1662547720602},{"msg":"指令执行结束","cdtNum":0,"ts":1662547720614},{"msg":"输入框文本变化","text":"新建圆形在这里使得它的文本为明","ts":1662547721900},{"msg":"输入框文本变化","text":"新建圆形在这里使得它的文本为","ts":1662547722074},{"msg":"输入框文本变化","text":"新建圆形在这里使得它的文本为暗暗","ts":1662547724413},{"msg":"开始语音输入","ts":1662547726968},{"msg":"识别结束","uttr":"","ts":1662547728842},{"msg":"识别结束","uttr":"","ts":1662547730180},{"msg":"识别结束","uttr":"","ts":1662547731632},{"msg":"识别结束","uttr":"","ts":1662547733110},{"msg":"识别结束","uttr":"","ts":1662547734622},{"msg":"识别结束","uttr":"","ts":1662547737626},{"msg":"识别结束","uttr":"","ts":1662547740628},{"msg":"结束语音输入","ts":1662547743597},{"msg":"识别结束","uttr":"","ts":1662547743620},{"msg":"开始语音输入","ts":1662547746089},{"msg":"识别结束","uttr":"","ts":1662547747678},{"msg":"结束语音输入","ts":1662547752766},{"msg":"识别结束","uttr":"建圆形在这里使得它的文本为案","ts":1662547753050},{"msg":"识别结束","uttr":"建圆形在这里使得它的文本为案","ts":1662547753105},{"msg":"输入框文本变化","text":"建圆形在这里使得它的文本为","ts":1662547755000},{"msg":"输入框文本变化","text":"建圆形在这里使得它的文本为暗","ts":1662547756851},{"msg":"输入框文本变化","text":"建圆形在这里使得它的文本为暗暗","ts":1662547758015},{"msg":"输入框文本变化","text":"新建圆形在这里使得它的文本为暗暗","ts":1662547760536},{"msg":"系统接收指令输入","uttr":"新建圆形在这里使得它的文本为暗暗","traceNum":1,"ts":1662547765064},{"msg":"解析结束","create":true,"copy":false,"arrow":false,"traceEleNum":0,"tracePosNum":1,"involvedEleNum":2,"itEleNum":0,"attrChange":1,"posRelated":true,"ts":1662547765087},{"msg":"指令执行结束","cdtNum":0,"ts":1662547765099},{"msg":"输入框文本变化","text":"新建圆形在这里使得它的文本为暗","ts":1662547772101},{"msg":"输入框文本变化","text":"新建圆形在这里使得它的文本为","ts":1662547772153},{"msg":"输入框文本变化","text":"新建圆形在这里使得它的文本","ts":1662547772225},{"msg":"输入框文本变化","text":"新建圆形在这里使得它的文","ts":1662547772276},{"msg":"输入框文本变化","text":"新建圆形在这里使得它的","ts":1662547772328},{"msg":"输入框文本变化","text":"新建圆形在这里使得它","ts":1662547772384},{"msg":"输入框文本变化","text":"新建圆形在这里使得","ts":1662547772442},{"msg":"输入框文本变化","text":"新建圆形在这里使","ts":1662547772496},{"msg":"输入框文本变化","text":"新建圆形在这里","ts":1662547772554},{"msg":"输入框文本变化","text":"新建圆形在这","ts":1662547772612},{"msg":"输入框文本变化","text":"新建圆形在","ts":1662547772678},{"msg":"输入框文本变化","text":"新建圆形","ts":1662547772730},{"msg":"输入框文本变化","text":"新建圆","ts":1662547772785},{"msg":"输入框文本变化","text":"新建","ts":1662547772840},{"msg":"输入框文本变化","text":"新","ts":1662547772895},{"msg":"输入框文本变化","text":"","ts":1662547772954},{"msg":"开始语音输入","ts":1662547775040},{"msg":"结束语音输入","ts":1662547778205},{"msg":"识别结束","uttr":"修改这个的颜色浅一点","ts":1662547778347},{"msg":"识别结束","uttr":"修改这个的颜色浅一点","ts":1662547778361},{"msg":"选中图表元素","ts":1662547781907},{"msg":"系统接收指令输入","uttr":"修改这个的颜色浅一点","traceNum":1,"ts":1662547783057},{"msg":"解析结束","create":false,"copy":false,"arrow":false,"traceEleNum":1,"tracePosNum":0,"involvedEleNum":1,"itEleNum":1,"attrChange":1,"ts":1662547783082},{"msg":"指令执行结束","cdtNum":0,"ts":1662547783096},{"msg":"选中图表元素","ts":1662547783986},{"msg":"系统接收指令输入","uttr":"修改这个的颜色浅一点","traceNum":1,"ts":1662547784524},{"msg":"解析结束","create":false,"copy":false,"arrow":false,"traceEleNum":1,"tracePosNum":0,"involvedEleNum":1,"itEleNum":1,"attrChange":1,"ts":1662547784549},{"msg":"指令执行结束","cdtNum":0,"ts":1662547784559},{"msg":"选中图表元素","ts":1662547786120},{"msg":"系统接收指令输入","uttr":"修改这个的颜色浅一点","traceNum":1,"ts":1662547786618},{"msg":"解析结束","create":false,"copy":false,"arrow":false,"traceEleNum":1,"tracePosNum":0,"involvedEleNum":1,"itEleNum":1,"attrChange":1,"ts":1662547786647},{"msg":"指令执行结束","cdtNum":0,"ts":1662547786657},{"msg":"选中图表元素","ts":1662547787084},{"msg":"系统接收指令输入","uttr":"修改这个的颜色浅一点","traceNum":1,"ts":1662547787649},{"msg":"解析结束","create":false,"copy":false,"arrow":false,"traceEleNum":1,"tracePosNum":0,"involvedEleNum":1,"itEleNum":1,"attrChange":1,"ts":1662547787681},{"msg":"指令执行结束","cdtNum":0,"ts":1662547787690},{"msg":"选中图表元素","ts":1662547790101},{"msg":"系统接收指令输入","uttr":"修改这个的颜色浅一点","traceNum":1,"ts":1662547790541},{"msg":"解析结束","create":false,"copy":false,"arrow":false,"traceEleNum":1,"tracePosNum":0,"involvedEleNum":1,"itEleNum":1,"attrChange":1,"ts":1662547790565},{"msg":"指令执行结束","cdtNum":0,"ts":1662547790574},{"msg":"选中图表元素","ts":1662547790964},{"msg":"系统接收指令输入","uttr":"修改这个的颜色浅一点","traceNum":1,"ts":1662547791381},{"msg":"解析结束","create":false,"copy":false,"arrow":false,"traceEleNum":1,"tracePosNum":0,"involvedEleNum":1,"itEleNum":1,"attrChange":1,"ts":1662547791404},{"msg":"指令执行结束","cdtNum":0,"ts":1662547791411},{"msg":"输入框文本变化","text":"修改这个的颜色一点","ts":1662547794653},{"msg":"输入框文本变化","text":"修改这个的颜色深一点","ts":1662547796525},{"msg":"选中图表元素","ts":1662547800809},{"msg":"系统接收指令输入","uttr":"修改这个的颜色深一点","traceNum":1,"ts":1662547803340},{"msg":"解析结束","create":false,"copy":false,"arrow":false,"traceEleNum":1,"tracePosNum":0,"involvedEleNum":1,"itEleNum":1,"attrChange":1,"ts":1662547803363},{"msg":"指令执行结束","cdtNum":0,"ts":1662547803405},{"msg":"选中图表元素","ts":1662547803961},{"msg":"系统接收指令输入","uttr":"修改这个的颜色深一点","traceNum":1,"ts":1662547804507},{"msg":"解析结束","create":false,"copy":false,"arrow":false,"traceEleNum":1,"tracePosNum":0,"involvedEleNum":1,"itEleNum":1,"attrChange":1,"ts":1662547804558},{"msg":"指令执行结束","cdtNum":0,"ts":1662547804567},{"msg":"选中图表元素","ts":1662547804991},{"msg":"系统接收指令输入","uttr":"修改这个的颜色深一点","traceNum":1,"ts":1662547805531},{"msg":"解析结束","create":false,"copy":false,"arrow":false,"traceEleNum":1,"tracePosNum":0,"involvedEleNum":1,"itEleNum":1,"attrChange":1,"ts":1662547805565},{"msg":"指令执行结束","cdtNum":0,"ts":1662547805574},{"msg":"选中图表元素","ts":1662547806034},{"msg":"系统接收指令输入","uttr":"修改这个的颜色深一点","traceNum":1,"ts":1662547806617},{"msg":"解析结束","create":false,"copy":false,"arrow":false,"traceEleNum":1,"tracePosNum":0,"involvedEleNum":1,"itEleNum":1,"attrChange":1,"ts":1662547806650},{"msg":"指令执行结束","cdtNum":0,"ts":1662547806657},{"msg":"选中图表元素","ts":1662547807700},{"msg":"系统接收指令输入","uttr":"修改这个的颜色深一点","traceNum":1,"ts":1662547808158},{"msg":"解析结束","create":false,"copy":false,"arrow":false,"traceEleNum":1,"tracePosNum":0,"involvedEleNum":1,"itEleNum":1,"attrChange":1,"ts":1662547808186},{"msg":"指令执行结束","cdtNum":0,"ts":1662547808193},{"msg":"选中图表元素","ts":1662547808690},{"msg":"系统接收指令输入","uttr":"修改这个的颜色深一点","traceNum":1,"ts":1662547809211},{"msg":"解析结束","create":false,"copy":false,"arrow":false,"traceEleNum":1,"tracePosNum":0,"involvedEleNum":1,"itEleNum":1,"attrChange":1,"ts":1662547809244},{"msg":"指令执行结束","cdtNum":0,"ts":1662547809251},{"msg":"选中图表元素","ts":1662547812097},{"msg":"系统接收指令输入","uttr":"修改这个的颜色深一点","traceNum":1,"ts":1662547812532},{"msg":"解析结束","create":false,"copy":false,"arrow":false,"traceEleNum":1,"tracePosNum":0,"involvedEleNum":1,"itEleNum":1,"attrChange":1,"ts":1662547812563},{"msg":"指令执行结束","cdtNum":0,"ts":1662547812570},{"msg":"选中图表元素","ts":1662547813266},{"msg":"系统接收指令输入","uttr":"修改这个的颜色深一点","traceNum":1,"ts":1662547813777},{"msg":"解析结束","create":false,"copy":false,"arrow":false,"traceEleNum":1,"tracePosNum":0,"involvedEleNum":1,"itEleNum":1,"attrChange":1,"ts":1662547813806},{"msg":"指令执行结束","cdtNum":0,"ts":1662547813814},{"msg":"选中图表元素","ts":1662547814268},{"msg":"系统接收指令输入","uttr":"修改这个的颜色深一点","traceNum":1,"ts":1662547814754},{"msg":"解析结束","create":false,"copy":false,"arrow":false,"traceEleNum":1,"tracePosNum":0,"involvedEleNum":1,"itEleNum":1,"attrChange":1,"ts":1662547814790},{"msg":"指令执行结束","cdtNum":0,"ts":1662547814796},{"msg":"结束对元素的拖拽","ts":1662547819260},{"msg":"指令执行结束","cdtNum":0,"ts":1662547819289},{"msg":"结束对元素的拖拽","ts":1662547821462},{"msg":"指令执行结束","cdtNum":0,"ts":1662547821495},{"msg":"结束对元素的拖拽","ts":1662547823108},{"msg":"指令执行结束","cdtNum":0,"ts":1662547823139},{"msg":"结束对元素的拖拽","ts":1662547825773},{"msg":"指令执行结束","cdtNum":0,"ts":1662547825806},{"msg":"结束对元素的拖拽","ts":1662547829239},{"msg":"指令执行结束","cdtNum":0,"ts":1662547829269},{"msg":"切换功能栏TAG_DISP_SET_GLOBAL","ts":1662547838579},{"msg":"清空路径","ts":1662547839442},{"msg":"开始语音输入","ts":1662547843153},{"msg":"结束语音输入","ts":1662547846567},{"msg":"识别结束","uttr":"新建连接这个和这个的箭头","ts":1662547846868},{"msg":"识别结束","uttr":"新建连接这个和这个的箭头","ts":1662547846890},{"msg":"选中图表元素","ts":1662547851961},{"msg":"选中图表元素","ts":1662547852461},{"msg":"系统接收指令输入","uttr":"新建连接这个和这个的箭头","traceNum":2,"ts":1662547854166},{"msg":"解析结束","create":false,"copy":false,"arrow":true,"arrowOp":"new","traceEleNum":2,"tracePosNum":0,"involvedEleNum":2,"itEleNum":2,"attrChange":0,"ts":1662547854207},{"msg":"指令执行结束","cdtNum":0,"ts":1662547854218},{"msg":"选中图表元素","ts":1662547855237},{"msg":"选中图表元素","ts":1662547855611},{"msg":"系统接收指令输入","uttr":"新建连接这个和这个的箭头","traceNum":2,"ts":1662547856595},{"msg":"解析结束","create":false,"copy":false,"arrow":true,"arrowOp":"new","traceEleNum":2,"tracePosNum":0,"involvedEleNum":2,"itEleNum":2,"attrChange":0,"ts":1662547856654},{"msg":"指令执行结束","cdtNum":0,"ts":1662547856662},{"msg":"选中图表元素","ts":1662547858148},{"msg":"选中图表元素","ts":1662547858382},{"msg":"系统接收指令输入","uttr":"新建连接这个和这个的箭头","traceNum":2,"ts":1662547858846},{"msg":"解析结束","create":false,"copy":false,"arrow":true,"arrowOp":"new","traceEleNum":2,"tracePosNum":0,"involvedEleNum":2,"itEleNum":2,"attrChange":0,"ts":1662547858890},{"msg":"指令执行结束","cdtNum":0,"ts":1662547858897},{"msg":"选中图表元素","ts":1662547859340},{"msg":"选中图表元素","ts":1662547859631},{"msg":"系统接收指令输入","uttr":"新建连接这个和这个的箭头","traceNum":2,"ts":1662547860230},{"msg":"解析结束","create":false,"copy":false,"arrow":true,"arrowOp":"new","traceEleNum":2,"tracePosNum":0,"involvedEleNum":2,"itEleNum":2,"attrChange":0,"ts":1662547860271},{"msg":"指令执行结束","cdtNum":0,"ts":1662547860280},{"msg":"选中图表元素","ts":1662547861979},{"msg":"选中图表元素","ts":1662547862297},{"msg":"系统接收指令输入","uttr":"新建连接这个和这个的箭头","traceNum":2,"ts":1662547863001},{"msg":"解析结束","create":false,"copy":false,"arrow":true,"arrowOp":"new","traceEleNum":2,"tracePosNum":0,"involvedEleNum":2,"itEleNum":2,"attrChange":0,"ts":1662547863045},{"msg":"指令执行结束","cdtNum":0,"ts":1662547863054},{"msg":"选中图表元素","ts":1662547865183},{"msg":"选中图表元素","ts":1662547865700},{"msg":"系统接收指令输入","uttr":"新建连接这个和这个的箭头","traceNum":2,"ts":1662547867240},{"msg":"解析结束","create":false,"copy":false,"arrow":true,"arrowOp":"new","traceEleNum":2,"tracePosNum":0,"involvedEleNum":2,"itEleNum":2,"attrChange":0,"ts":1662547867283},{"msg":"指令执行结束","cdtNum":0,"ts":1662547867291},{"msg":"选中图表元素","ts":1662547868691},{"msg":"选中图表元素","ts":1662547869021},{"msg":"系统接收指令输入","uttr":"新建连接这个和这个的箭头","traceNum":2,"ts":1662547869685},{"msg":"解析结束","create":false,"copy":false,"arrow":true,"arrowOp":"new","traceEleNum":2,"tracePosNum":0,"involvedEleNum":2,"itEleNum":2,"attrChange":0,"ts":1662547869739},{"msg":"指令执行结束","cdtNum":0,"ts":1662547869745},{"msg":"选中图表元素","ts":1662547870288},{"msg":"选中图表元素","ts":1662547870757},{"msg":"系统接收指令输入","uttr":"新建连接这个和这个的箭头","traceNum":2,"ts":1662547871391},{"msg":"解析结束","create":false,"copy":false,"arrow":true,"arrowOp":"new","traceEleNum":2,"tracePosNum":0,"involvedEleNum":2,"itEleNum":2,"attrChange":0,"ts":1662547871438},{"msg":"指令执行结束","cdtNum":0,"ts":1662547871446},{"msg":"选中图表元素","ts":1662547873417},{"msg":"选中图表元素","ts":1662547873861},{"msg":"系统接收指令输入","uttr":"新建连接这个和这个的箭头","traceNum":2,"ts":1662547874914},{"msg":"解析结束","create":false,"copy":false,"arrow":true,"arrowOp":"new","traceEleNum":2,"tracePosNum":0,"involvedEleNum":2,"itEleNum":2,"attrChange":0,"ts":1662547874963},{"msg":"指令执行结束","cdtNum":0,"ts":1662547874970},{"msg":"选中图表元素","ts":1662547876308},{"msg":"选中图表元素","ts":1662547879190},{"msg":"系统接收指令输入","uttr":"新建连接这个和这个的箭头","traceNum":2,"ts":1662547879910},{"msg":"解析结束","create":false,"copy":false,"arrow":true,"arrowOp":"new","traceEleNum":2,"tracePosNum":0,"involvedEleNum":2,"itEleNum":2,"attrChange":0,"ts":1662547879960},{"msg":"指令执行结束","cdtNum":0,"ts":1662547879968},{"msg":"选中图表元素","ts":1662547882159},{"msg":"选中图表元素","ts":1662547882857},{"msg":"系统接收指令输入","uttr":"新建连接这个和这个的箭头","traceNum":2,"ts":1662547883449},{"msg":"解析结束","create":false,"copy":false,"arrow":true,"arrowOp":"new","traceEleNum":2,"tracePosNum":0,"involvedEleNum":2,"itEleNum":2,"attrChange":0,"ts":1662547883495},{"msg":"指令执行结束","cdtNum":0,"ts":1662547883502},{"msg":"选中图表元素","ts":1662547884933},{"msg":"选中图表元素","ts":1662547885350},{"msg":"系统接收指令输入","uttr":"新建连接这个和这个的箭头","traceNum":2,"ts":1662547886033},{"msg":"解析结束","create":false,"copy":false,"arrow":true,"arrowOp":"new","traceEleNum":2,"tracePosNum":0,"involvedEleNum":2,"itEleNum":2,"attrChange":0,"ts":1662547886084},{"msg":"指令执行结束","cdtNum":0,"ts":1662547886091},{"msg":"输入框文本变化","text":"新建连接这个和这个的箭","ts":1662547900532},{"msg":"输入框文本变化","text":"新建连接这个和这个的","ts":1662547900582},{"msg":"输入框文本变化","text":"新建连接这个和这个","ts":1662547900637},{"msg":"输入框文本变化","text":"新建连接这个和这","ts":1662547900694},{"msg":"输入框文本变化","text":"新建连接这个和","ts":1662547900757},{"msg":"输入框文本变化","text":"新建连接这个","ts":1662547900811},{"msg":"输入框文本变化","text":"新建连接这","ts":1662547900861},{"msg":"输入框文本变化","text":"新建连接","ts":1662547900921},{"msg":"输入框文本变化","text":"新建连","ts":1662547900978},{"msg":"输入框文本变化","text":"新建","ts":1662547901034},{"msg":"输入框文本变化","text":"新","ts":1662547901086},{"msg":"输入框文本变化","text":"","ts":1662547901143},{"msg":"开始语音输入","ts":1662547902459},{"msg":"结束语音输入","ts":1662547905580},{"msg":"识别结束","uttr":"修改这个大大小小一点","ts":1662547905897},{"msg":"识别结束","uttr":"修改这个大大小小一点","ts":1662547905898},{"msg":"选中图表元素","ts":1662547908540},{"msg":"系统接收指令输入","uttr":"修改这个大大小小一点","traceNum":1,"ts":1662547909283},{"msg":"输入框文本变化","text":"修改这个的大大小小一点","ts":1662547915281},{"msg":"输入框文本变化","text":"修改这个的大小小一点","ts":1662547918019},{"msg":"系统接收指令输入","uttr":"修改这个的大小小一点","traceNum":1,"ts":1662547920319},{"msg":"解析结束","create":false,"copy":false,"arrow":false,"traceEleNum":1,"tracePosNum":0,"involvedEleNum":1,"itEleNum":1,"attrChange":1,"ts":1662547920411},{"msg":"指令执行结束","cdtNum":0,"ts":1662547920424},{"msg":"选中图表元素","ts":1662547921706},{"msg":"系统接收指令输入","uttr":"修改这个的大小小一点","traceNum":1,"ts":1662547922296},{"msg":"解析结束","create":false,"copy":false,"arrow":false,"traceEleNum":1,"tracePosNum":0,"involvedEleNum":1,"itEleNum":1,"attrChange":1,"ts":1662547922355},{"msg":"指令执行结束","cdtNum":0,"ts":1662547922363},{"msg":"选中图表元素","ts":1662547922825},{"msg":"系统接收指令输入","uttr":"修改这个的大小小一点","traceNum":1,"ts":1662547923370},{"msg":"解析结束","create":false,"copy":false,"arrow":false,"traceEleNum":1,"tracePosNum":0,"involvedEleNum":1,"itEleNum":1,"attrChange":1,"ts":1662547923427},{"msg":"指令执行结束","cdtNum":0,"ts":1662547923434},{"msg":"选中图表元素","ts":1662547923893},{"msg":"系统接收指令输入","uttr":"修改这个的大小小一点","traceNum":1,"ts":1662547924462},{"msg":"解析结束","create":false,"copy":false,"arrow":false,"traceEleNum":1,"tracePosNum":0,"involvedEleNum":1,"itEleNum":1,"attrChange":1,"ts":1662547924517},{"msg":"指令执行结束","cdtNum":0,"ts":1662547924524},{"msg":"切换功能栏TAG_DISP_SET_GLOBAL","ts":1662547934742}]