[{"msg":"开始语音输入","ts":1661925211847},{"msg":"结束语音输入","ts":1661925213621},{"msg":"识别结束","uttr":"新建元素在这里","ts":1661925213951},{"msg":"识别结束","uttr":"新建元素在这里","ts":1661925213984},{"msg":"系统接收指令输入","uttr":"新建元素在这里","traceNum":1,"ts":1661925216045},{"msg":"解析结束","create":true,"copy":false,"arrow":false,"traceEleNum":0,"tracePosNum":1,"involvedEleNum":1,"itEleNum":0,"attrChange":0,"posRelated":true,"ts":1661925216073},{"msg":"指令执行结束","cdtNum":1,"ts":1661925216120},{"msg":"系统接收指令输入","uttr":"新建元素在这里","traceNum":2,"ts":1661925231421},{"msg":"解析结束","create":true,"copy":false,"arrow":false,"traceEleNum":0,"tracePosNum":1,"involvedEleNum":1,"itEleNum":0,"attrChange":0,"posRelated":true,"ts":1661925231446},{"msg":"指令执行结束","cdtNum":1,"ts":1661925231492},{"msg":"系统接收指令输入","uttr":"新建元素在这里","traceNum":1,"ts":1661925235491},{"msg":"解析结束","create":true,"copy":false,"arrow":false,"traceEleNum":0,"tracePosNum":1,"involvedEleNum":1,"itEleNum":0,"attrChange":0,"posRelated":true,"ts":1661925235528},{"msg":"指令执行结束","cdtNum":2,"ts":1661925235604},{"msg":"系统接收指令输入","uttr":"新建元素在这里","traceNum":1,"ts":1661925237243},{"msg":"解析结束","create":true,"copy":false,"arrow":false,"traceEleNum":0,"tracePosNum":1,"involvedEleNum":1,"itEleNum":0,"attrChange":0,"posRelated":true,"ts":1661925237278},{"msg":"指令执行结束","cdtNum":3,"ts":1661925237351},{"msg":"开始语音输入","ts":1661925244659},{"msg":"结束语音输入","ts":1661925248009},{"msg":"识别结束","uttr":"修改使得这个的纵坐标等于这个的纵坐标","ts":1661925248211},{"msg":"识别结束","uttr":"修改使得这个的纵坐标等于这个的纵坐标","ts":1661925248229},{"msg":"选中图表元素","ts":1661925249342},{"msg":"选中图表元素","ts":1661925250166},{"msg":"系统接收指令输入","uttr":"修改使得这个的纵坐标等于这个的纵坐标","traceNum":2,"ts":1661925251604},{"msg":"解析结束","create":false,"copy":false,"arrow":false,"traceEleNum":2,"tracePosNum":0,"involvedEleNum":2,"itEleNum":2,"attrChange":0,"posRelated":true,"ts":1661925251645},{"msg":"指令执行结束","cdtNum":2,"ts":1661925251726},{"msg":"选中图表元素","ts":1661925255247},{"msg":"开始语音输入","ts":1661925261443},{"msg":"结束语音输入","ts":1661925266785},{"msg":"识别结束","uttr":"修改使得这个和这个的水平距离等于这个和这个的水平距离","ts":1661925266951},{"msg":"识别结束","uttr":"修改使得这个和这个的水平距离等于这个和这个的水平距离","ts":1661925266977},{"msg":"选中图表元素","ts":1661925269089},{"msg":"取消元素选择","ts":1661925269955},{"msg":"选中图表元素","ts":1661925271557},{"msg":"选中图表元素","ts":1661925272420},{"msg":"系统接收指令输入","uttr":"修改使得这个和这个的水平距离等于这个和这个的水平距离","traceNum":4,"ts":1661925274414},{"msg":"解析结束","create":false,"copy":false,"arrow":false,"traceEleNum":4,"tracePosNum":0,"involvedEleNum":4,"itEleNum":4,"attrChange":0,"posRelated":true,"ts":1661925274452},{"msg":"指令执行结束","cdtNum":1,"ts":1661925274500},{"msg":"开始语音输入","ts":1661925291710},{"msg":"结束语音输入","ts":1661925293600},{"msg":"识别结束","uttr":"新建元素在这里","ts":1661925293824},{"msg":"识别结束","uttr":"新建元素在这里","ts":1661925293848},{"msg":"系统接收指令输入","uttr":"新建元素在这里","traceNum":1,"ts":1661925300495},{"msg":"解析结束","create":true,"copy":false,"arrow":false,"traceEleNum":0,"tracePosNum":1,"involvedEleNum":1,"itEleNum":0,"attrChange":0,"posRelated":true,"ts":1661925300525},{"msg":"指令执行结束","cdtNum":1,"ts":1661925300582},{"msg":"系统接收指令输入","uttr":"新建元素在这里","traceNum":1,"ts":1661925302739},{"msg":"解析结束","create":true,"copy":false,"arrow":false,"traceEleNum":0,"tracePosNum":1,"involvedEleNum":1,"itEleNum":0,"attrChange":0,"posRelated":true,"ts":1661925302784},{"msg":"指令执行结束","cdtNum":1,"ts":1661925302858},{"msg":"选中图表元素","ts":1661925310260},{"msg":"开始语音输入","ts":1661925326754},{"msg":"结束语音输入","ts":1661925331777},{"msg":"识别结束","uttr":"修改使得这个和这个的水平距离等于这个和这个的竖直距离","ts":1661925332213},{"msg":"识别结束","uttr":"修改使得这个和这个的水平距离等于这个和这个的竖直距离","ts":1661925332234},{"msg":"选中图表元素","ts":1661925335499},{"msg":"取消元素选择","ts":1661925336440},{"msg":"选中图表元素","ts":1661925338242},{"msg":"选中图表元素","ts":1661925338979},{"msg":"系统接收指令输入","uttr":"修改使得这个和这个的水平距离等于这个和这个的竖直距离","traceNum":4,"ts":1661925340010},{"msg":"解析结束","create":false,"copy":false,"arrow":false,"traceEleNum":4,"tracePosNum":0,"involvedEleNum":4,"itEleNum":4,"attrChange":0,"posRelated":true,"ts":1661925340035},{"msg":"指令执行结束","cdtNum":6,"ts":1661925340126},{"msg":"开始语音输入","ts":1661925349068},{"msg":"结束语音输入","ts":1661925351655},{"msg":"识别结束","uttr":"新建元素在这里","ts":1661925351920},{"msg":"识别结束","uttr":"新建元素在这里","ts":1661925351944},{"msg":"系统接收指令输入","uttr":"新建元素在这里","traceNum":1,"ts":1661925355474},{"msg":"解析结束","create":true,"copy":false,"arrow":false,"traceEleNum":0,"tracePosNum":1,"involvedEleNum":1,"itEleNum":0,"attrChange":0,"posRelated":true,"ts":1661925355498},{"msg":"指令执行结束","cdtNum":8,"ts":1661925355616},{"msg":"系统接收指令输入","uttr":"新建元素在这里","traceNum":1,"ts":1661925357191},{"msg":"解析结束","create":true,"copy":false,"arrow":false,"traceEleNum":0,"tracePosNum":1,"involvedEleNum":1,"itEleNum":0,"attrChange":0,"posRelated":true,"ts":1661925357228},{"msg":"指令执行结束","cdtNum":15,"ts":1661925357404},{"msg":"选择候选","idx":1,"length":15,"ts":1661925364056},{"msg":"选择候选","idx":2,"length":15,"ts":1661925364930},{"msg":"选择候选","idx":2,"length":15,"ts":1661925367973},{"msg":"选中图表元素","ts":1661925369648},{"msg":"选中图表元素","ts":1661925371269},{"msg":"选中图表元素","ts":1661925372829},{"msg":"选中图表元素","ts":1661925373989},{"msg":"开始语音输入","ts":1661925381959},{"msg":"结束语音输入","ts":1661925386321},{"msg":"识别结束","uttr":"修改使得这个和这个的横坐标相同","ts":1661925386474},{"msg":"识别结束","uttr":"修改使得这个和这个的横坐标相同","ts":1661925386492},{"msg":"开始语音输入","ts":1661925404126},{"msg":"结束语音输入","ts":1661925407753},{"msg":"识别结束","uttr":"修改使得这个的横坐标等于这个横坐标","ts":1661925408056},{"msg":"识别结束","uttr":"修改使得这个的横坐标等于这个横坐标","ts":1661925408077},{"msg":"选中图表元素","ts":1661925413578},{"msg":"取消元素选择","ts":1661925415116},{"msg":"系统接收指令输入","uttr":"修改使得这个的横坐标等于这个横坐标","traceNum":2,"ts":1661925416091},{"msg":"系统接收指令输入","uttr":"修改使得这个的横坐标等于这个的横坐标","traceNum":2,"ts":1661925425569},{"msg":"解析结束","create":false,"copy":false,"arrow":false,"traceEleNum":2,"tracePosNum":0,"involvedEleNum":2,"itEleNum":2,"attrChange":0,"posRelated":true,"ts":1661925425600},{"msg":"指令执行结束","cdtNum":17,"ts":1661925425920},{"msg":"选中图表元素","ts":1661925428972},{"msg":"取消元素选择","ts":1661925429887},{"msg":"开始语音输入","ts":1661925433595},{"msg":"结束语音输入","ts":1661925437934},{"msg":"识别结束","uttr":"修改使得这个的纵坐标对于这个的纵坐标","ts":1661925438312},{"msg":"识别结束","uttr":"修改使得这个的纵坐标对于这个的纵坐标","ts":1661925438332},{"msg":"选中图表元素","ts":1661925439601},{"msg":"选中图表元素","ts":1661925440278},{"msg":"系统接收指令输入","uttr":"修改使得这个的纵坐标对于这个的纵坐标","traceNum":2,"ts":1661925440970},{"msg":"选中图表元素","ts":1661925448102},{"msg":"取消元素选择","ts":1661925448745},{"msg":"系统接收指令输入","uttr":"修改使得这个的纵坐标等于这个的纵坐标","traceNum":4,"ts":1661925449921},{"msg":"解析结束","create":false,"copy":false,"arrow":false,"traceEleNum":2,"tracePosNum":0,"involvedEleNum":2,"itEleNum":2,"attrChange":0,"posRelated":true,"ts":1661925449959},{"msg":"指令执行结束","cdtNum":9,"ts":1661925450083},{"msg":"选中图表元素","ts":1661925452525},{"msg":"取消元素选择","ts":1661925458953},{"msg":"开始语音输入","ts":1661925463576},{"msg":"结束语音输入","ts":1661925466979},{"msg":"识别结束","uttr":"新建元素在这个和这个的中点","ts":1661925467192},{"msg":"识别结束","uttr":"新建元素在这个和这个的中点","ts":1661925467213},{"msg":"选中图表元素","ts":1661925468288},{"msg":"选中图表元素","ts":1661925469248},{"msg":"系统接收指令输入","uttr":"新建元素在这个和这个的中点","traceNum":2,"ts":1661925470319},{"msg":"解析结束","create":true,"copy":false,"arrow":false,"traceEleNum":2,"tracePosNum":0,"involvedEleNum":3,"itEleNum":2,"attrChange":0,"posRelated":true,"ts":1661925470352},{"msg":"指令执行结束","cdtNum":1,"ts":1661925470400},{"msg":"开始语音输入","ts":1661925475216},{"msg":"结束语音输入","ts":1661925477623},{"msg":"识别结束","uttr":"修改这个的颜色为红色","ts":1661925477833},{"msg":"识别结束","uttr":"修改这个的颜色为红色","ts":1661925477848},{"msg":"系统接收指令输入","uttr":"修改这个的颜色为红色","traceNum":1,"ts":1661925479497},{"msg":"解析结束","create":false,"copy":false,"arrow":false,"traceEleNum":1,"tracePosNum":0,"involvedEleNum":1,"itEleNum":1,"attrChange":1,"ts":1661925479537},{"msg":"指令执行结束","cdtNum":1,"ts":1661925479555},{"msg":"开始语音输入","ts":1661925491743},{"msg":"结束语音输入","ts":1661925494251},{"msg":"识别结束","uttr":"新建连接这个和这个的直线","ts":1661925494624},{"msg":"识别结束","uttr":"新建连接这个和这个的直线","ts":1661925494654},{"msg":"选中图表元素","ts":1661925496062},{"msg":"选中图表元素","ts":1661925496731},{"msg":"系统接收指令输入","uttr":"新建连接这个和这个的直线","traceNum":2,"ts":1661925497427},{"msg":"解析结束","create":false,"copy":false,"arrow":true,"arrowOp":"new","traceEleNum":2,"tracePosNum":0,"involvedEleNum":2,"itEleNum":2,"attrChange":0,"ts":1661925497462},{"msg":"指令执行结束","cdtNum":1,"ts":1661925497487},{"msg":"选中图表元素","ts":1661925498749},{"msg":"系统接收指令输入","uttr":"新建连接这个和这个的直线","traceNum":2,"ts":1661925499659},{"msg":"解析结束","create":false,"copy":false,"arrow":true,"arrowOp":"new","traceEleNum":2,"tracePosNum":0,"involvedEleNum":2,"itEleNum":2,"attrChange":0,"ts":1661925499714},{"msg":"指令执行结束","cdtNum":1,"ts":1661925499738},{"msg":"选中图表元素","ts":1661925500552},{"msg":"选中图表元素","ts":1661925501248},{"msg":"系统接收指令输入","uttr":"新建连接这个和这个的直线","traceNum":2,"ts":1661925502971},{"msg":"解析结束","create":false,"copy":false,"arrow":true,"arrowOp":"new","traceEleNum":2,"tracePosNum":0,"involvedEleNum":2,"itEleNum":2,"attrChange":0,"ts":1661925503021},{"msg":"指令执行结束","cdtNum":1,"ts":1661925503052},{"msg":"选中图表元素","ts":1661925504143},{"msg":"系统接收指令输入","uttr":"新建连接这个和这个的直线","traceNum":2,"ts":1661925505003},{"msg":"解析结束","create":false,"copy":false,"arrow":true,"arrowOp":"new","traceEleNum":2,"tracePosNum":0,"involvedEleNum":2,"itEleNum":2,"attrChange":0,"ts":1661925505055},{"msg":"指令执行结束","cdtNum":1,"ts":1661925505072},{"msg":"选中图表元素","ts":1661925506975},{"msg":"系统接收指令输入","uttr":"新建连接这个和这个的直线","traceNum":2,"ts":1661925507744},{"msg":"解析结束","create":false,"copy":false,"arrow":true,"arrowOp":"new","traceEleNum":2,"tracePosNum":0,"involvedEleNum":2,"itEleNum":2,"attrChange":0,"ts":1661925507780},{"msg":"指令执行结束","cdtNum":1,"ts":1661925507801},{"msg":"系统接收指令输入","uttr":"新建连接这个和这个的直线","traceNum":2,"ts":1661925509986},{"msg":"解析结束","create":false,"copy":false,"arrow":true,"arrowOp":"new","traceEleNum":2,"tracePosNum":0,"involvedEleNum":2,"itEleNum":2,"attrChange":0,"ts":1661925510013},{"msg":"指令执行结束","cdtNum":1,"ts":1661925510034},{"msg":"选中图表元素","ts":1661925510566},{"msg":"选中图表元素","ts":1661925511154},{"msg":"系统接收指令输入","uttr":"新建连接这个和这个的直线","traceNum":2,"ts":1661925511943},{"msg":"解析结束","create":false,"copy":false,"arrow":true,"arrowOp":"new","traceEleNum":2,"tracePosNum":0,"involvedEleNum":2,"itEleNum":2,"attrChange":0,"ts":1661925511981},{"msg":"指令执行结束","cdtNum":1,"ts":1661925512006},{"msg":"选中图表元素","ts":1661925512795},{"msg":"系统接收指令输入","uttr":"新建连接这个和这个的直线","traceNum":2,"ts":1661925514356},{"msg":"解析结束","create":false,"copy":false,"arrow":true,"arrowOp":"new","traceEleNum":2,"tracePosNum":0,"involvedEleNum":2,"itEleNum":2,"attrChange":0,"ts":1661925514411},{"msg":"指令执行结束","cdtNum":1,"ts":1661925514435},{"msg":"选中图表元素","ts":1661925514980},{"msg":"选中图表元素","ts":1661925515569},{"msg":"系统接收指令输入","uttr":"新建连接这个和这个的直线","traceNum":2,"ts":1661925516565},{"msg":"解析结束","create":false,"copy":false,"arrow":true,"arrowOp":"new","traceEleNum":2,"tracePosNum":0,"involvedEleNum":2,"itEleNum":2,"attrChange":0,"ts":1661925516617},{"msg":"指令执行结束","cdtNum":1,"ts":1661925516638},{"msg":"选中图表元素","ts":1661925517397},{"msg":"系统接收指令输入","uttr":"新建连接这个和这个的直线","traceNum":2,"ts":1661925518477},{"msg":"解析结束","create":false,"copy":false,"arrow":true,"arrowOp":"new","traceEleNum":2,"tracePosNum":0,"involvedEleNum":2,"itEleNum":2,"attrChange":0,"ts":1661925518514},{"msg":"指令执行结束","cdtNum":1,"ts":1661925518532},{"msg":"选中图表元素","ts":1661925519019},{"msg":"选中图表元素","ts":1661925519811},{"msg":"系统接收指令输入","uttr":"新建连接这个和这个的直线","traceNum":2,"ts":1661925520778},{"msg":"解析结束","create":false,"copy":false,"arrow":true,"arrowOp":"new","traceEleNum":2,"tracePosNum":0,"involvedEleNum":2,"itEleNum":2,"attrChange":0,"ts":1661925520840},{"msg":"指令执行结束","cdtNum":1,"ts":1661925520867},{"msg":"选中图表元素","ts":1661925521442},{"msg":"选中图表元素","ts":1661925522173},{"msg":"系统接收指令输入","uttr":"新建连接这个和这个的直线","traceNum":2,"ts":1661925522888},{"msg":"解析结束","create":false,"copy":false,"arrow":true,"arrowOp":"new","traceEleNum":2,"tracePosNum":0,"involvedEleNum":2,"itEleNum":2,"attrChange":0,"ts":1661925522936},{"msg":"指令执行结束","cdtNum":1,"ts":1661925522957},{"msg":"选中图表元素","ts":1661925526790},{"msg":"系统接收指令输入","uttr":"新建连接这个和这个的直线","traceNum":2,"ts":1661925527815},{"msg":"解析结束","create":false,"copy":false,"arrow":true,"arrowOp":"new","traceEleNum":2,"tracePosNum":0,"involvedEleNum":2,"itEleNum":2,"attrChange":0,"ts":1661925527883},{"msg":"指令执行结束","cdtNum":1,"ts":1661925527908},{"msg":"选中图表元素","ts":1661925528865},{"msg":"选中图表元素","ts":1661925529775},{"msg":"系统接收指令输入","uttr":"新建连接这个和这个的直线","traceNum":2,"ts":1661925530571},{"msg":"解析结束","create":false,"copy":false,"arrow":true,"arrowOp":"new","traceEleNum":2,"tracePosNum":0,"involvedEleNum":2,"itEleNum":2,"attrChange":0,"ts":1661925530617},{"msg":"指令执行结束","cdtNum":1,"ts":1661925530636},{"msg":"选中图表元素","ts":1661925531336},{"msg":"选中图表元素","ts":1661925532298},{"msg":"系统接收指令输入","uttr":"新建连接这个和这个的直线","traceNum":2,"ts":1661925533179},{"msg":"解析结束","create":false,"copy":false,"arrow":true,"arrowOp":"new","traceEleNum":2,"tracePosNum":0,"involvedEleNum":2,"itEleNum":2,"attrChange":0,"ts":1661925533258},{"msg":"指令执行结束","cdtNum":1,"ts":1661925533287},{"msg":"开始语音输入","ts":1661925539436},{"msg":"结束语音输入","ts":1661925543405},{"msg":"识别结束","uttr":"修改连接这个和这个的直线为虚线","ts":1661925543642},{"msg":"识别结束","uttr":"修改连接这个和这个的直线为虚线","ts":1661925543669},{"msg":"选中图表元素","ts":1661925545956},{"msg":"选中图表元素","ts":1661925546951},{"msg":"系统接收指令输入","uttr":"修改连接这个和这个的直线为虚线","traceNum":2,"ts":1661925547923},{"msg":"解析结束","create":false,"copy":false,"arrow":true,"arrowOp":"change","traceEleNum":2,"tracePosNum":0,"involvedEleNum":2,"itEleNum":2,"attrChange":0,"ts":1661925547971},{"msg":"指令执行结束","cdtNum":1,"ts":1661925547990},{"msg":"选中图表元素","ts":1661925549060},{"msg":"选中图表元素","ts":1661925549840},{"msg":"系统接收指令输入","uttr":"修改连接这个和这个的直线为虚线","traceNum":2,"ts":1661925550505},{"msg":"解析结束","create":false,"copy":false,"arrow":true,"arrowOp":"change","traceEleNum":2,"tracePosNum":0,"involvedEleNum":2,"itEleNum":2,"attrChange":0,"ts":1661925550569},{"msg":"指令执行结束","cdtNum":1,"ts":1661925550592},{"msg":"选中图表元素","ts":1661925551117},{"msg":"选中图表元素","ts":1661925551911},{"msg":"系统接收指令输入","uttr":"修改连接这个和这个的直线为虚线","traceNum":2,"ts":1661925552356},{"msg":"解析结束","create":false,"copy":false,"arrow":true,"arrowOp":"change","traceEleNum":2,"tracePosNum":0,"involvedEleNum":2,"itEleNum":2,"attrChange":0,"ts":1661925552411},{"msg":"指令执行结束","cdtNum":1,"ts":1661925552432},{"msg":"选中图表元素","ts":1661925554494},{"msg":"系统接收指令输入","uttr":"修改连接这个和这个的直线为虚线","traceNum":2,"ts":1661925555263},{"msg":"解析结束","create":false,"copy":false,"arrow":true,"arrowOp":"change","traceEleNum":2,"tracePosNum":0,"involvedEleNum":2,"itEleNum":2,"attrChange":0,"ts":1661925555347},{"msg":"指令执行结束","cdtNum":1,"ts":1661925555367},{"msg":"选中图表元素","ts":1661925556367},{"msg":"选中图表元素","ts":1661925557088},{"msg":"系统接收指令输入","uttr":"修改连接这个和这个的直线为虚线","traceNum":2,"ts":1661925557851},{"msg":"解析结束","create":false,"copy":false,"arrow":true,"arrowOp":"change","traceEleNum":2,"tracePosNum":0,"involvedEleNum":2,"itEleNum":2,"attrChange":0,"ts":1661925557884},{"msg":"指令执行结束","cdtNum":1,"ts":1661925557901},{"msg":"选中图表元素","ts":1661925558577},{"msg":"选中图表元素","ts":1661925559255},{"msg":"系统接收指令输入","uttr":"修改连接这个和这个的直线为虚线","traceNum":2,"ts":1661925560008},{"msg":"解析结束","create":false,"copy":false,"arrow":true,"arrowOp":"change","traceEleNum":2,"tracePosNum":0,"involvedEleNum":2,"itEleNum":2,"attrChange":0,"ts":1661925560075},{"msg":"指令执行结束","cdtNum":1,"ts":1661925560096},{"msg":"切换功能栏TAG_DISP_SET_GLOBAL","ts":1661925572811}]